[{"course_name":"习近平外交思想与全面推进中国特色大国外交（上）","courseware_device":2,"lecturer":"赵可金","lecturer_introduction":"清华大学社会科学学院副院长、全球共同发展研究院副院长","usercourseid":0,"assessement_type":0,"rating_score":"9.7","duration":40,"category_id":77,"org_id":1,"online_date":"2020-03-03","id":5018,"course_no":"n51944071","cover_image":"n51944071logo.png","completed_count":10645,"full_path":"/选修课程/理论武装/习近平新时代中国特色社会主义思想","learning_hour":"1.0"},{"course_name":"习近平外交思想与全面推进中国特色大国外交（中）","courseware_device":2,"lecturer":"赵可金","lecturer_introduction":"清华大学社会科学学院副院长、全球共同发展研究院副院长","usercourseid":0,"assessement_type":0,"rating_score":"9.8","duration":38,"category_id":77,"org_id":1,"online_date":"2020-03-03","id":5019,"course_no":"n51944081","cover_image":"n51944081logo.png","completed_count":10038,"full_path":"/选修课程/理论武装/习近平新时代中国特色社会主义思想","learning_hour":"1.0"},{"course_name":"习近平外交思想与全面推进中国特色大国外交（下）","courseware_device":2,"lecturer":"赵可金","lecturer_introduction":"清华大学社会科学学院副院长、全球共同发展研究院副院长","usercourseid":0,"assessement_type":0,"rating_score":"9.5","duration":22,"category_id":77,"org_id":1,"online_date":"2020-03-03","id":5020,"course_no":"n51944091","cover_image":"n51944091logo.png","completed_count":9795,"full_path":"/选修课程/理论武装/习近平新时代中国特色社会主义思想","learning_hour":"0.5"},{"course_name":"改革开放与中国特色社会主义（上）","courseware_device":2,"lecturer":"郭建宁","lecturer_introduction":"北京大学马克思主义学院教授 博士生导师","usercourseid":0,"assessement_type":0,"rating_score":"9.6","duration":50,"category_id":77,"org_id":1,"online_date":"2020-01-15","id":4821,"course_no":"jx2001012","cover_image":"jx2001012logo.png","completed_count":15546,"full_path":"/选修课程/理论武装/习近平新时代中国特色社会主义思想","learning_hour":"1.5"},{"course_name":"改革开放与中国特色社会主义（下）","courseware_device":2,"lecturer":"郭建宁","lecturer_introduction":"北京大学马克思主义学院教授 博士生导师","usercourseid":0,"assessement_type":0,"rating_score":"9.5","duration":46,"category_id":77,"org_id":1,"online_date":"2020-01-15","id":4822,"course_no":"jx2001013","cover_image":"jx2001013logo.png","completed_count":9611,"full_path":"/选修课程/理论武装/习近平新时代中国特色社会主义思想","learning_hour":"1.0"},{"course_name":"学习贯彻习近平新时代中国特色社会主义思想（上）","courseware_device":2,"lecturer":"李建国","lecturer_introduction":"中国社会科学院马克思主义研究院研究员","usercourseid":0,"assessement_type":0,"rating_score":"9.4","duration":45,"category_id":77,"org_id":1,"online_date":"2020-01-15","id":4848,"course_no":"jx2001041","cover_image":"jx2001041logo.png","completed_count":8444,"full_path":"/选修课程/理论武装/习近平新时代中国特色社会主义思想","learning_hour":"1.0"},{"course_name":"学习贯彻习近平新时代中国特色社会主义思想（下）","courseware_device":2,"lecturer":"李建国","lecturer_introduction":"中国社会科学院马克思主义研究院研究员","usercourseid":0,"assessement_type":0,"rating_score":"9.6","duration":45,"category_id":77,"org_id":1,"online_date":"2020-01-15","id":4849,"course_no":"jx2001042","cover_image":"jx2001042logo.png","completed_count":7650,"full_path":"/选修课程/理论武装/习近平新时代中国特色社会主义思想","learning_hour":"1.0"},{"course_name":"习近平生态文明思想的科学内涵与实施路径（上）","courseware_device":2,"lecturer":"张玉虎","lecturer_introduction":"首都师范大学副教授","usercourseid":0,"assessement_type":0,"rating_score":"9.6","duration":55,"category_id":77,"org_id":1,"online_date":"2020-01-15","id":4850,"course_no":"jx2001043","cover_image":"jx2001043logo.png","completed_count":11077,"full_path":"/选修课程/理论武装/习近平新时代中国特色社会主义思想","learning_hour":"1.5"},{"course_name":"习近平生态文明思想的科学内涵与实施路径（下）","courseware_device":2,"lecturer":"张玉虎","lecturer_introduction":"首都师范大学副教授","usercourseid":0,"assessement_type":0,"rating_score":"9.6","duration":55,"category_id":77,"org_id":1,"online_date":"2020-01-15","id":4851,"course_no":"jx2001044","cover_image":"jx2001044logo.png","completed_count":10935,"full_path":"/选修课程/理论武装/习近平新时代中国特色社会主义思想","learning_hour":"1.5"},{"course_name":"习近平新时代中国特色社会主义思想在福建的孕育与实践","courseware_device":2,"lecturer":"陈新","lecturer_introduction":"中共福建省委党校（福建行政学院）经济学教研部副主任、教授","usercourseid":0,"assessement_type":0,"rating_score":"9.7","duration":93,"category_id":77,"org_id":1,"online_date":"2020-01-15","id":4899,"course_no":"p21936041","cover_image":"p21936041logo.png","completed_count":16529,"full_path":"/选修课程/理论武装/习近平新时代中国特色社会主义思想","learning_hour":"2.0"},{"course_name":"习近平生态文明思想的科学体系与指导意义","courseware_device":2,"lecturer":"张云飞","lecturer_introduction":"中国人民大学马克思主义学院教授","usercourseid":0,"assessement_type":0,"rating_score":"9.9","duration":142,"category_id":77,"org_id":1,"online_date":"2019-09-18","id":4512,"course_no":"zz1940021","cover_image":"zz1940021logo.png","completed_count":21266,"full_path":"/选修课程/理论武装/习近平新时代中国特色社会主义思想","learning_hour":"3.5"},{"course_name":"“八八战略”：从浙江实践到治国方略","courseware_device":2,"lecturer":"徐明华","lecturer_introduction":"浙江省委党校副校长、浙江行政学院副院长","usercourseid":0,"assessement_type":0,"rating_score":"9.8","duration":86,"category_id":77,"org_id":1,"online_date":"2019-08-19","id":4465,"course_no":"p21936031","cover_image":"p21936031logo.png","completed_count":10759,"full_path":"/选修课程/理论武装/习近平新时代中国特色社会主义思想","learning_hour":"2.0"},{"course_name":"习近平新时代中国特色社会主义思想正定探源","courseware_device":2,"lecturer":"祁刚利","lecturer_introduction":"中共河北省委党校（河北行政学院）中共党史教研部副主任、教授","usercourseid":0,"assessement_type":0,"rating_score":"9.6","duration":76,"category_id":77,"org_id":1,"online_date":"2019-07-19","id":4383,"course_no":"p21936021","cover_image":"p21936021logo.png","completed_count":108338,"full_path":"/选修课程/理论武装/习近平新时代中国特色社会主义思想","learning_hour":"1.5"},{"course_name":"习近平新时代中国特色社会主义经济思想","courseware_device":2,"lecturer":"谢鲁江","lecturer_introduction":"中共中央党校（国家行政学院）经济学教研部教授","usercourseid":0,"assessement_type":0,"rating_score":"9.6","duration":102,"category_id":77,"org_id":1,"online_date":"2019-06-28","id":4174,"course_no":"zx1951141","cover_image":"zx1951141logo.png","completed_count":16212,"full_path":"/选修课程/理论武装/习近平新时代中国特色社会主义思想","learning_hour":"2.5"},{"course_name":"习近平新时代中国特色社会主义思想概论","courseware_device":2,"lecturer":"倪德刚","lecturer_introduction":"中共中央党校（国家行政学院）科学社会主义教研部副主任、教授","usercourseid":0,"assessement_type":0,"rating_score":"9.7","duration":78,"category_id":77,"org_id":1,"online_date":"2019-06-28","id":4175,"course_no":"zx1951121","cover_image":"zx1951121logo.png","completed_count":121652,"full_path":"/选修课程/理论武装/习近平新时代中国特色社会主义思想","learning_hour":"2.0"},{"course_name":"习近平总书记全面依法治国新理念新思想新战略","courseware_device":2,"lecturer":"王轶","lecturer_introduction":"中国人民大学法学院院长、教授","usercourseid":0,"assessement_type":0,"rating_score":"9.5","duration":81,"category_id":77,"org_id":1,"online_date":"2019-06-28","id":4176,"course_no":"tl1901051","cover_image":"tl1901051logo.png","completed_count":123311,"full_path":"/选修课程/理论武装/习近平新时代中国特色社会主义思想","learning_hour":"2.0"},{"course_name":"习近平总书记关于加强和改进统一战线工作的重要论述（上）","courseware_device":2,"lecturer":"孙信","lecturer_introduction":"中央社会主义学院统战理论教研部主任","usercourseid":0,"assessement_type":0,"rating_score":"9.8","duration":47,"category_id":77,"org_id":1,"online_date":"2019-06-20","id":4197,"course_no":"zj1906103","cover_image":"zj1906103logo.png","completed_count":5588,"full_path":"/选修课程/理论武装/习近平新时代中国特色社会主义思想","learning_hour":"1.5"},{"course_name":"习近平总书记关于加强和改进统一战线工作的重要论述（下）","courseware_device":2,"lecturer":"孙信","lecturer_introduction":"中央社会主义学院统战理论教研部主任","usercourseid":0,"assessement_type":0,"rating_score":"9.7","duration":55,"category_id":77,"org_id":1,"online_date":"2019-06-20","id":4198,"course_no":"zj1906104","cover_image":"zj1906104logo.png","completed_count":4458,"full_path":"/选修课程/理论武装/习近平新时代中国特色社会主义思想","learning_hour":"1.5"},{"course_name":"习近平总书记构建人类命运共同体思想的渊源和发展","courseware_device":2,"lecturer":"陈向阳","lecturer_introduction":"中国现代国际关系研究院危机管理研究中心主任","usercourseid":0,"assessement_type":0,"rating_score":"9.8","duration":35,"category_id":77,"org_id":1,"online_date":"2019-05-20","id":4106,"course_no":"jy1905206","cover_image":"jy1905206logo.png","completed_count":7041,"full_path":"/选修课程/理论武装/习近平新时代中国特色社会主义思想","learning_hour":"1.0"},{"course_name":"习近平总体国家安全观","courseware_device":2,"lecturer":"罗建波","lecturer_introduction":"中共中央党校（国家行政学院）国际战略研究院教授","usercourseid":0,"assessement_type":0,"rating_score":"9.4","duration":100,"category_id":77,"org_id":1,"online_date":"2019-05-17","id":4091,"course_no":"zx1951071","cover_image":"zx1951071logo.png","completed_count":5962,"full_path":"/选修课程/理论武装/习近平新时代中国特色社会主义思想","learning_hour":"2.5"},{"course_name":"习近平总书记关于全面深化改革的重要论述","courseware_device":2,"lecturer":"李鹏","lecturer_introduction":"中共中央党校（国家行政学院）经济学教研部教授","usercourseid":0,"assessement_type":0,"rating_score":"9.6","duration":92,"category_id":77,"org_id":1,"online_date":"2019-05-17","id":4089,"course_no":"zx1951041","cover_image":"zx1951041logo.png","completed_count":4069,"full_path":"/选修课程/理论武装/习近平新时代中国特色社会主义思想","learning_hour":"2.0"},{"course_name":"习近平新时代中国特色社会主义外交思想","courseware_device":2,"lecturer":"宫力","lecturer_introduction":"中共中央党校（国家行政学院）国际战略研究院教授","usercourseid":0,"assessement_type":0,"rating_score":"9.6","duration":84,"category_id":77,"org_id":1,"online_date":"2019-05-17","id":4087,"course_no":"zx1951021","cover_image":"zx1951021logo.png","completed_count":5006,"full_path":"/选修课程/理论武装/习近平新时代中国特色社会主义思想","learning_hour":"2.0"},{"course_name":"习近平总书记关于社会建设的重要论述","courseware_device":2,"lecturer":"王道勇","lecturer_introduction":"中共中央党校（国家行政学院）社会和生态文明教研部教授","usercourseid":0,"assessement_type":0,"rating_score":"9.9","duration":85,"category_id":77,"org_id":1,"online_date":"2019-05-17","id":4090,"course_no":"zx1951031","cover_image":"zx1951031logo.png","completed_count":4442,"full_path":"/选修课程/理论武装/习近平新时代中国特色社会主义思想","learning_hour":"2.0"},{"course_name":"习近平总书记关于科技创新的重要论述","courseware_device":2,"lecturer":"高志前","lecturer_introduction":"中国科学技术发展战略研究院研究员","usercourseid":0,"assessement_type":0,"rating_score":"9.9","duration":80,"category_id":77,"org_id":1,"online_date":"2019-05-17","id":4088,"course_no":"zx1951061","cover_image":"zx1951061logo.png","completed_count":4269,"full_path":"/选修课程/理论武装/习近平新时代中国特色社会主义思想","learning_hour":"2.0"},{"course_name":"习近平生态文明思想","courseware_device":2,"lecturer":"赵建军","lecturer_introduction":"中共中央党校（国家行政学院）哲学部教授，博士生导师","usercourseid":0,"assessement_type":0,"rating_score":"9.8","duration":101,"category_id":77,"org_id":1,"online_date":"2019-05-17","id":4086,"course_no":"zx1951011","cover_image":"zx1951011logo.png","completed_count":9444,"full_path":"/选修课程/理论武装/习近平新时代中国特色社会主义思想","learning_hour":"2.5"}]